restkiss/__init__.py
restkiss/constants.py
restkiss/data.py
restkiss/dj.py
restkiss/exceptions.py
restkiss/fl.py
restkiss/it.py
restkiss/preparers.py
restkiss/pyr.py
restkiss/resources.py
restkiss/serializers.py
restkiss/tnd.py
restkiss/utils.py
restkiss-2.0.2.dist-info/DESCRIPTION.rst
restkiss-2.0.2.dist-info/METADATA
restkiss-2.0.2.dist-info/RECORD
restkiss-2.0.2.dist-info/WHEEL
restkiss-2.0.2.dist-info/metadata.json
restkiss-2.0.2.dist-info/top_level.txt
